{
  "relationships_dismissed_suggested_users": [
    {
      "title": "",
      "media_list_data": [
        
      ],
      "string_list_data": [
        {
          "href": "https://www.instagram.com/_deshani_484_",
          "value": "_deshani_484_",
          "timestamp": 1682008540
        }
      ]
    },
    {
      "title": "",
      "media_list_data": [
        
      ],
      "string_list_data": [
        {
          "href": "https://www.instagram.com/keshu___st___",
          "value": "keshu___st___",
          "timestamp": 1682008539
        }
      ]
    },
    {
      "title": "",
      "media_list_data": [
        
      ],
      "string_list_data": [
        {
          "href": "https://www.instagram.com/dewwbe_",
          "value": "dewwbe_",
          "timestamp": 1682008538
        }
      ]
    },
    {
      "title": "",
      "media_list_data": [
        
      ],
      "string_list_data": [
        {
          "href": "https://www.instagram.com/chathu_mi__",
          "value": "chathu_mi__",
          "timestamp": 1682008537
        }
      ]
    },
    {
      "title": "",
      "media_list_data": [
        
      ],
      "string_list_data": [
        {
          "href": "https://www.instagram.com/chathu_0513",
          "value": "chathu_0513",
          "timestamp": 1682008533
        }
      ]
    },
    {
      "title": "",
      "media_list_data": [
        
      ],
      "string_list_data": [
        {
          "href": "https://www.instagram.com/madhushika_bandara",
          "value": "madhushika_bandara",
          "timestamp": 1682008532
        }
      ]
    },
    {
      "title": "",
      "media_list_data": [
        
      ],
      "string_list_data": [
        {
          "href": "https://www.instagram.com/kuvishi_",
          "value": "kuvishi_",
          "timestamp": 1682008531
        }
      ]
    },
    {
      "title": "",
      "media_list_data": [
        
      ],
      "string_list_data": [
        {
          "href": "https://www.instagram.com/chanul_domila",
          "value": "chanul_domila",
          "timestamp": 1682008529
        }
      ]
    },
    {
      "title": "",
      "media_list_data": [
        
      ],
      "string_list_data": [
        {
          "href": "https://www.instagram.com/niumiyohansa",
          "value": "niumiyohansa",
          "timestamp": 1682008528
        }
      ]
    },
    {
      "title": "",
      "media_list_data": [
        
      ],
      "string_list_data": [
        {
          "href": "https://www.instagram.com/dilshanshashika367",
          "value": "dilshanshashika367",
          "timestamp": 1682008527
        }
      ]
    }
  ]
}